pycheese/__init__.py
pycheese/args.py
pycheese/render.py
pycheese/fonts/JetBrainsMono-Bold.ttf
pycheese/fonts/JetBrainsMono-BoldItalic.ttf
pycheese/fonts/JetBrainsMono-Italic.ttf
pycheese/fonts/JetBrainsMono-Regular.ttf
pycheese/fonts/font_config.toml
pycheese/utils/__init__.py
pycheese/utils/fonts.py
pycheese/utils/image.py
pycheese/utils/linewrap.py
pycheese/utils/linewrap_core.py
pycheese-0.3.2.dist-info/METADATA
pycheese-0.3.2.dist-info/WHEEL
pycheese-0.3.2.dist-info/entry_points.txt
pycheese-0.3.2.dist-info/licenses/LICENSE
pycheese-0.3.2.dist-info/RECORD
