Metadata-Version: 2.4
Name: pycheese
Version: 0.3.2
Summary: Generate beautiful images of code with syntax highlighting in a stylish terminal window.
Project-URL: Homepage, https://github.com/krautlabs/pycheese
Author-email: Krautlabs <dev@krautlabs.com>
License:                     GNU GENERAL PUBLIC LICENSE
License-File: LICENSE
Classifier: Intended Audience :: Developers
Classifier: License :: OSI Approved :: GNU General Public License v3 (GPLv3)
Classifier: Operating System :: OS Independent
Classifier: Programming Language :: Python :: 3
Classifier: Topic :: Software Development :: Documentation
Classifier: Topic :: Utilities
Requires-Python: >=3.11
Requires-Dist: pillow>=11.2.1
Requires-Dist: pygments>=2.19.1
Requires-Dist: tomli-w>=1.2.0
